ocp_vscode/__init__.py
ocp_vscode/__main__.py
ocp_vscode/animation.py
ocp_vscode/backend.py
ocp_vscode/backend_logo.py
ocp_vscode/colors.py
ocp_vscode/comms.py
ocp_vscode/config.py
ocp_vscode/measure.py
ocp_vscode/selectors.py
ocp_vscode/show.py
ocp_vscode/standalone.py
ocp_vscode/state.py
ocp_vscode/static/css/three-cad-viewer.css
ocp_vscode/static/js/comms.js
ocp_vscode/static/js/logo.js
ocp_vscode/static/js/three-cad-viewer.esm.js
ocp_vscode/templates/viewer.html
ocp_vscode-3.0.0.dist-info/licenses/LICENSE
ocp_vscode-3.0.0.dist-info/METADATA
ocp_vscode-3.0.0.dist-info/WHEEL
ocp_vscode-3.0.0.dist-info/top_level.txt
ocp_vscode-3.0.0.dist-info/RECORD
