Metadata-Version: 2.4
Name: ocp_vscode
Version: 3.0.0
Summary: OCP CAD Viewer for VSCode
Author-email: Bernhard Walter <b_walter@arcor.de>
License-Expression: Apache-2.0
Project-URL: Homepage, https://github.com/bernhard-42/vscode-ocp-cad-viewer
Project-URL: Bug Tracker, https://github.com/bernhard-42/vscode-ocp-cad-viewer/issues
Keywords: 3d models,3d printing,3d viewing,3d,brep,cad,cadquery,opencscade,python
Classifier: Operating System :: OS Independent
Classifier: Programming Language :: Python :: 3
Requires-Python: >=3.9
License-File: LICENSE
Requires-Dist: ocp-tessellate<3.2.0,>=3.1.0
Requires-Dist: requests
Requires-Dist: ipykernel
Requires-Dist: orjson
Requires-Dist: websockets<14.0,>=13.0
Requires-Dist: pyaml
Requires-Dist: flask<4.0,>=3.0
Requires-Dist: flask_sock<1.0,>=0.7
Requires-Dist: click<9.0,>=8.1
Requires-Dist: pyperclip==1.9.0
Requires-Dist: questionary==2.1.1
Provides-Extra: dev
Requires-Dist: questionary~=1.10.0; extra == "dev"
Requires-Dist: bump-my-version; extra == "dev"
Requires-Dist: ruff; extra == "dev"
Requires-Dist: twine; extra == "dev"
Dynamic: license-file
